full/__about__.py
full/__init__.py
full/eval.py
full-0.0.3.1.dist-info/METADATA
full-0.0.3.1.dist-info/WHEEL
full-0.0.3.1.dist-info/licenses/LICENSE.txt
full-0.0.3.1.dist-info/RECORD
