Metadata-Version: 2.1
Name: full
Version: 0.0.3.1
Project-URL: Documentation, https://github.com/maximedb/full
Project-URL: Issues, https://github.com/maximedb/full
Project-URL: Source, https://github.com/maximedb/full
Author-email: maximedb <maxime.debruyn@uantwerpen.be>
License-File: LICENSE.txt
Classifier: Development Status :: 4 - Beta
Classifier: Programming Language :: Python
Classifier: Programming Language :: Python :: 3.7
Classifier: Programming Language :: Python :: 3.8
Classifier: Programming Language :: Python :: 3.9
Classifier: Programming Language :: Python :: 3.10
Classifier: Programming Language :: Python :: 3.11
Classifier: Programming Language :: Python :: Implementation :: CPython
Classifier: Programming Language :: Python :: Implementation :: PyPy
Requires-Python: >=3.7
Requires-Dist: torch
Requires-Dist: transformers
